[
  {
    "id": 1,
    "filename": " Snip Snap  ",
    "name": " Snip Snap  ",
    "x": -13971.06,
    "y": 228786.38,
    "z": 2169.59
  },
  {
    "id": 2,
    "filename": "  Snip Snap  ",
    "name": "  Snip Snap  ",
    "x": -106245.59,
    "y": 96761.52,
    "z": 6537.83
  },
  {
    "id": 3,
    "filename": "  Snip Snap  ",
    "name": "  Snip Snap  ",
    "x": -15117.43,
    "y": 62548.31,
    "z": 162.52
  },
  {
    "id": 4,
    "filename": "Snip Snap  ",
    "name": "Snip Snap  ",
    "x": 80817.14,
    "y": 266308.19,
    "z": 4529.62
  },
  {
    "id": 5,
    "filename": " Snip Snap  0",
    "name": " Snip Snap  0",
    "x": -43625.4,
    "y": -4089.59,
    "z": 20425.77
  },
  {
    "id": 6,
    "filename": "Snip Snap  ",
    "name": "Snip Snap  ",
    "x": -99985.05,
    "y": 67948.33,
    "z": 5663
  },
  {
    "id": 7,
    "filename": " Snip Snap  ",
    "name": " Snip Snap  ",
    "x": -99784.05,
    "y": 67470.5,
    "z": 5584.39
  },
  {
    "id": 8,
    "filename": "Snip Snap  ",
    "name": "Snip Snap  ",
    "x": -11413.12,
    "y": 182272.2,
    "z": -25.01
  },
  {
    "id": 9,
    "filename": "Snip Snap  ",
    "name": "Snip Snap  ",
    "x": -162889.54,
    "y": 189050.84,
    "z": 291.27
  },
  {
    "id": 10,
    "filename": "Snip Snap  ",
    "name": "Snip Snap  ",
    "x": -55365.01,
    "y": 267592.34,
    "z": 8341.99
  },
  {
    "id": 11,
    "filename": " Snip Snap  ",
    "name": " Snip Snap  ",
    "x": -132407.26,
    "y": 221895,
    "z": 180.41
  },
  {
    "id": 12,
    "filename": " Snip Snap  ",
    "name": " Snip Snap  ",
    "x": 44018.98,
    "y": 318067.56,
    "z": 880.21
  },
  {
    "id": 13,
    "filename": " Snip Snap  ",
    "name": " Snip Snap  ",
    "x": -144126.29,
    "y": 225999.11,
    "z": 120.23
  },
  {
    "id": 14,
    "filename": " Snip Snap  ",
    "name": " Snip Snap  ",
    "x": -55365.01,
    "y": 267592.34,
    "z": 8341.99
  },
  {
    "id": 15,
    "filename": " Snip Snap  ",
    "name": " Snip Snap  ",
    "x": -120375.55,
    "y": 228521.5,
    "z": 242.33
  },
  {
    "id": 16,
    "filename": "Snip Snap  ",
    "name": "Snip Snap  ",
    "x": 25432.08,
    "y": 271327.4,
    "z": 3170.65
  },
  {
    "id": 17,
    "filename": " Snip Snap  ",
    "name": " Snip Snap  ",
    "x": 25611.73,
    "y": 270623.15,
    "z": 3219.63
  },
  {
    "id": 18,
    "filename": " Snip Snap  ",
    "name": " Snip Snap  ",
    "x": 26112.91,
    "y": 271125.69,
    "z": 3170.65
  },
  {
    "id": 19,
    "filename": " Snip Snap  ",
    "name": " Snip Snap  ",
    "x": 40998.57,
    "y": 274320.25,
    "z": 3714.29
  },
  {
    "id": 20,
    "filename": " Snip Snap  ",
    "name": " Snip Snap  ",
    "x": 40755.07,
    "y": 274603.9,
    "z": 3681.37
  },
  {
    "id": 21,
    "filename": " Snip Snap  ",
    "name": " Snip Snap  ",
    "x": 74423,
    "y": 282921.34,
    "z": 5834.91
  },
  {
    "id": 22,
    "filename": " Snip Snap  ",
    "name": " Snip Snap  ",
    "x": 75153.84,
    "y": 282946.69,
    "z": 5817.22
  },
  {
    "id": 23,
    "filename": " Snip Snap  ",
    "name": " Snip Snap  ",
    "x": -3583.52,
    "y": -50568.34,
    "z": 20493.91
  },
  {
    "id": 24,
    "filename": " Snip Snap  ",
    "name": " Snip Snap  ",
    "x": -3511.46,
    "y": -50197.05,
    "z": 20486.21
  },
  {
    "id": 25,
    "filename": " Snip Snap  ",
    "name": " Snip Snap  ",
    "x": -25705.72,
    "y": -60007.86,
    "z": 21550.1
  },
  {
    "id": 26,
    "filename": " Snip Snap  ",
    "name": " Snip Snap  ",
    "x": 16770.13,
    "y": -45867.24,
    "z": 13114.45
  },
  {
    "id": 27,
    "filename": " Snip Snap  ",
    "name": " Snip Snap  ",
    "x": -128735.71,
    "y": 221851.5,
    "z": 21.5
  },
  {
    "id": 28,
    "filename": "Snip Snap  ",
    "name": "Snip Snap  ",
    "x": -131293.59,
    "y": 225643.2,
    "z": 23.44
  },
  {
    "id": 29,
    "filename": " Snip Snap  ",
    "name": " Snip Snap  ",
    "x": -68669.23,
    "y": 27151.22,
    "z": 5784.4
  },
  {
    "id": 30,
    "filename": " Snip Snap  ",
    "name": " Snip Snap  ",
    "x": -68911.12,
    "y": 26870.85,
    "z": 5892.42
  },
  {
    "id": 31,
    "filename": "  Snip Snap  ",
    "name": "  Snip Snap  ",
    "x": -69068.75,
    "y": 27159.55,
    "z": 5816.4
  },
  {
    "id": 32,
    "filename": "  Snip Snap  ",
    "name": "  Snip Snap  ",
    "x": -43601.11,
    "y": 29268.8,
    "z": 7327.02
  },
  {
    "id": 33,
    "filename": "  Snip Snap  ",
    "name": "  Snip Snap  ",
    "x": -43619.73,
    "y": 29680.7,
    "z": 7210.84
  },
  {
    "id": 34,
    "filename": "  Snip Snap  ",
    "name": "  Snip Snap  ",
    "x": -43872.11,
    "y": 29488.77,
    "z": 7277.46
  },
  {
    "id": 35,
    "filename": "  Snip Snap  ",
    "name": "  Snip Snap  ",
    "x": -41108.8,
    "y": -14012.54,
    "z": 18836.04
  },
  {
    "id": 36,
    "filename": "  Snip Snap  ",
    "name": "  Snip Snap  ",
    "x": -90299.21,
    "y": 94164.27,
    "z": 6164.98
  },
  {
    "id": 37,
    "filename": " Snip Snap  ",
    "name": " Snip Snap  ",
    "x": 898.72,
    "y": 58737.5,
    "z": 282.19
  },
  {
    "id": 38,
    "filename": " Snip Snap  ",
    "name": " Snip Snap  ",
    "x": -96087,
    "y": 37814,
    "z": 7570
  },
  {
    "id": 39,
    "filename": " Snip Snap  0",
    "name": " Snip Snap  0",
    "x": -95464,
    "y": 39288,
    "z": 7779
  },
  {
    "id": 40,
    "filename": " Snip Snap  1",
    "name": " Snip Snap  1",
    "x": -95242,
    "y": 38014,
    "z": 7848
  },
  {
    "id": 41,
    "filename": " Snip Snap  0",
    "name": " Snip Snap  0",
    "x": -27201.88,
    "y": 60887.25,
    "z": 5136.87
  },
  {
    "id": 42,
    "filename": " Snip Snap  1",
    "name": " Snip Snap  1",
    "x": -27783.29,
    "y": 60922.54,
    "z": 5202.1
  },
  {
    "id": 43,
    "filename": "  Snip Snap  ",
    "name": "  Snip Snap  ",
    "x": -27568.17,
    "y": 61392.03,
    "z": 5137.35
  },
  {
    "id": 44,
    "filename": "Snip Snap  ",
    "name": "Snip Snap  ",
    "x": 32990,
    "y": 214640,
    "z": 240
  },
  {
    "id": 45,
    "filename": " Snip Snap  ",
    "name": " Snip Snap  ",
    "x": 32990,
    "y": 213550,
    "z": 240
  },
  {
    "id": 46,
    "filename": " Snip Snap  ",
    "name": " Snip Snap  ",
    "x": 33570,
    "y": 214380,
    "z": 240
  },
  {
    "id": 47,
    "filename": " Snip Snap  ",
    "name": " Snip Snap  ",
    "x": 32640,
    "y": 214780,
    "z": 240
  },
  {
    "id": 48,
    "filename": " Snip Snap  ",
    "name": " Snip Snap  ",
    "x": 32450,
    "y": 213760,
    "z": 240
  },
  {
    "id": 49,
    "filename": "  Snip Snap  ",
    "name": "  Snip Snap  ",
    "x": 6164.24,
    "y": 216278.41,
    "z": 1390.4
  },
  {
    "id": 50,
    "filename": " Snip Snap  0",
    "name": " Snip Snap  0",
    "x": 6090.98,
    "y": 216487.89,
    "z": 1390.4
  },
  {
    "id": 51,
    "filename": " Snip Snap  ",
    "name": " Snip Snap  ",
    "x": -49841.49,
    "y": 228752.83,
    "z": 7187.4
  },
  {
    "id": 52,
    "filename": " Snip Snap  ",
    "name": " Snip Snap  ",
    "x": -1190.21,
    "y": 154605.09,
    "z": 77.7
  },
  {
    "id": 53,
    "filename": " Snip Snap  ",
    "name": " Snip Snap  ",
    "x": -906.55,
    "y": 154633.82,
    "z": 79.67
  },
  {
    "id": 54,
    "filename": " Snip Snap  ",
    "name": " Snip Snap  ",
    "x": -736.87,
    "y": 154859.97,
    "z": 79.68
  },
  {
    "id": 55,
    "filename": "Snip Snap  ",
    "name": "Snip Snap  ",
    "x": 92047.16,
    "y": -88714.35,
    "z": -6.69
  },
  {
    "id": 56,
    "filename": " Snip Snap  ",
    "name": " Snip Snap  ",
    "x": 45608.84,
    "y": -105610.51,
    "z": 51.58
  },
  {
    "id": 57,
    "filename": " Snip Snap  ",
    "name": " Snip Snap  ",
    "x": 60483,
    "y": -71900,
    "z": 581
  },
  {
    "id": 58,
    "filename": " Snip Snap  ",
    "name": " Snip Snap  ",
    "x": 55052.99,
    "y": -117482.98,
    "z": 788.05
  },
  {
    "id": 59,
    "filename": " Snip Snap  ",
    "name": " Snip Snap  ",
    "x": 59499,
    "y": -82340.99,
    "z": 39.26
  },
  {
    "id": 60,
    "filename": " Snip Snap  ",
    "name": " Snip Snap  ",
    "x": 51260,
    "y": -87521,
    "z": 732
  },
  {
    "id": 61,
    "filename": " Snip Snap  ",
    "name": " Snip Snap  ",
    "x": 46056,
    "y": -82954,
    "z": 61
  },
  {
    "id": 62,
    "filename": "Snip Snap  ",
    "name": "Snip Snap  ",
    "x": -98956.33,
    "y": 81819.19,
    "z": 4175
  },
  {
    "id": 63,
    "filename": " Snip Snap  ",
    "name": " Snip Snap  ",
    "x": -98799.84,
    "y": 82013.46,
    "z": 4130.14
  },
  {
    "id": 64,
    "filename": " Snip Snap  ",
    "name": " Snip Snap  ",
    "x": -32380,
    "y": -31720,
    "z": 20300
  },
  {
    "id": 65,
    "filename": " Snip Snap  ",
    "name": " Snip Snap  ",
    "x": -19873.24,
    "y": -65211.2,
    "z": 21823.51
  },
  {
    "id": 66,
    "filename": "Snip Snap  ",
    "name": "Snip Snap  ",
    "x": -18500.68,
    "y": -66287.45,
    "z": 22356.92
  },
  {
    "id": 67,
    "filename": " Snip Snap  ",
    "name": " Snip Snap  ",
    "x": -19033.5,
    "y": -66599.64,
    "z": 22369.54
  },
  {
    "id": 68,
    "filename": " Snip Snap  ",
    "name": " Snip Snap  ",
    "x": -2980.28,
    "y": -64628.8,
    "z": 15212
  },
  {
    "id": 69,
    "filename": " Snip Snap  ",
    "name": " Snip Snap  ",
    "x": -3257.42,
    "y": -65120.76,
    "z": 15222
  },
  {
    "id": 70,
    "filename": " Snip Snap  ",
    "name": " Snip Snap  ",
    "x": -22995.78,
    "y": -55496.64,
    "z": 20657.55
  },
  {
    "id": 71,
    "filename": " Snip Snap  0",
    "name": " Snip Snap  0",
    "x": -11646.78,
    "y": -72615.64,
    "z": 21356.91
  },
  {
    "id": 72,
    "filename": " Snip Snap  ",
    "name": " Snip Snap  ",
    "x": -51664.9,
    "y": 60348.31,
    "z": 4922.29
  }
]
